erads-0.1.7.dist-info/RECORD
erads-0.1.7.dist-info/METADATA
erads-0.1.7.dist-info/entry_points.txt
erads-0.1.7.dist-info/top_level.txt
erads-0.1.7.dist-info/DESCRIPTION.rst
erads-0.1.7.dist-info/metadata.json
erads-0.1.7.dist-info/WHEEL
erads/get_intraday_data_txt.py
erads/erads.py
erads/__init__.py
erads/command_line.py
erads-0.1.7.data/scripts/test
erads-0.1.7.data/scripts/get_intraday_data_txt
