Metadata-Version: 2.0
Name: erads
Version: 0.1.7
Summary: fetch data, a platform for era group
Home-page: https://github.com/gongshijun/erads
Author: gongshijun
Author-email: gongshijun@ict.ac.cn
License: MIT license
Keywords: erads
Platform: UNKNOWN
Classifier: Development Status :: 2 - Pre-Alpha
Classifier: Intended Audience :: Developers
Classifier: License :: OSI Approved :: MIT License
Classifier: Natural Language :: English
Classifier: Operating System :: OS Independent
Classifier: Programming Language :: Python :: 2
Classifier: Programming Language :: Python :: 2.6
Classifier: Programming Language :: Python :: 2.7
Classifier: Programming Language :: Python :: 3
Classifier: Programming Language :: Python :: 3.3
Classifier: Programming Language :: Python :: 3.4
Classifier: Programming Language :: Python :: 3.5
